{"generatedAt":"2026-06-28T09:38:25+09:00","retentionLimit":14,"snapshots":[{"id":"20260628","label":"2026-06-28","generatedAt":"2026-06-28T09:38:00+09:00","sourceAsOfDate":"20260628","currentMonth":"202606","manifestFile":"snapshots/20260628/manifest.json.gz","compressed":true},{"id":"20260627","label":"2026-06-27","generatedAt":"2026-06-27T09:37:53+09:00","sourceAsOfDate":"20260627","currentMonth":"202606","manifestFile":"snapshots/20260627/manifest.json.gz","compressed":true},{"id":"20260626","label":"2026-06-26","generatedAt":"2026-06-26T18:19:42+09:00","sourceAsOfDate":"20260626","currentMonth":"202606","manifestFile":"snapshots/20260626/manifest.json.gz","compressed":true}]}